cozi_client.py
exceptions.py
models.py
utils.py
py_cozi_client-1.3.0.dist-info/METADATA
py_cozi_client-1.3.0.dist-info/WHEEL
py_cozi_client-1.3.0.dist-info/top_level.txt
py_cozi_client-1.3.0.dist-info/RECORD
